prefect_redis/__init__.py
prefect_redis/_version.py
prefect_redis/blocks.py
prefect_redis/client.py
prefect_redis/lease_storage.py
prefect_redis/locking.py
prefect_redis/messaging.py
prefect_redis/ordering.py
prefect_redis/tasks.py
prefect_redis-0.2.8.dist-info/licenses/LICENSE
prefect_redis-0.2.8.dist-info/METADATA
prefect_redis-0.2.8.dist-info/WHEEL
prefect_redis-0.2.8.dist-info/entry_points.txt
prefect_redis-0.2.8.dist-info/top_level.txt
prefect_redis-0.2.8.dist-info/RECORD
